admin_smoke/__init__.py
admin_smoke/tests.py
django_admin_smoke-0.6.0.dist-info/licenses/LICENSE
django_admin_smoke-0.6.0.dist-info/METADATA
django_admin_smoke-0.6.0.dist-info/WHEEL
django_admin_smoke-0.6.0.dist-info/top_level.txt
django_admin_smoke-0.6.0.dist-info/RECORD
