Metadata-Version: 2.4
Name: django-admin-smoke
Version: 0.6.0
Summary: Smoke tests library for Django Admin
Author-email: Sergey Tikhonov <zimbler@gmail.com>
License: MIT
Project-URL: homepage, https://github.com/just-work/django-admin-smoke
Keywords: django,admin,smoke,tests
Classifier: Development Status :: 4 - Beta
Classifier: Environment :: Console
Classifier: Framework :: Django :: 3.2
Classifier: Framework :: Django :: 4.0
Classifier: Framework :: Django :: 4.1
Classifier: Framework :: Django :: 4.2
Classifier: Framework :: Django :: 5.0
Classifier: Framework :: Django :: 5.1
Classifier: Framework :: Django :: 5.2
Classifier: Operating System :: POSIX
Classifier: Programming Language :: Python :: 3.8
Classifier: Programming Language :: Python :: 3.9
Classifier: Programming Language :: Python :: 3.10
Classifier: Programming Language :: Python :: 3.11
Classifier: Programming Language :: Python :: 3.12
Classifier: Programming Language :: Python :: 3.13
Classifier: Topic :: Software Development :: Testing
License-File: LICENSE
Requires-Dist: Django<5.3,>=3.2
Requires-Dist: django-testing-utils~=0.8.0
Dynamic: license-file
